Classfile /F:/jpf/jpf-core/Test.class
  Last modified 21-Jul-2019; size 934 bytes
  MD5 checksum 07b271f34145e65c7cfc0b710c791a12
  Compiled from "Test.java"
public class Test
  minor version: 0
  major version: 55
  flags: (0x0021) ACC_PUBLIC, ACC_SUPER
  this_class: #7                          // Test
  super_class: #8                         // java/lang/Object
  interfaces: 0, fields: 0, methods: 3, attributes: 3
Constant pool:
   #1 = Methodref          #8.#19         // java/lang/Object."<init>":()V
   #2 = InvokeDynamic      #0:#23         // #0:makeConcatWithConstants:(Ljava/lang/String;)Ljava/lang/String;
   #3 = Fieldref           #24.#25        // java/lang/System.out:Ljava/io/PrintStream;
   #4 = Methodref          #26.#27        // java/io/PrintStream.println:(Ljava/lang/String;)V
   #5 = String             #28            // Hello
   #6 = Methodref          #7.#29         // Test.foo:(Ljava/lang/String;)V
   #7 = Class              #30            // Test
   #8 = Class              #31            // java/lang/Object
   #9 = Utf8               <init>
  #10 = Utf8               ()V
  #11 = Utf8               Code
  #12 = Utf8               LineNumberTable
  #13 = Utf8               foo
  #14 = Utf8               (Ljava/lang/String;)V
  #15 = Utf8               main
  #16 = Utf8               ([Ljava/lang/String;)V
  #17 = Utf8               SourceFile
  #18 = Utf8               Test.java
  #19 = NameAndType        #9:#10         // "<init>":()V
  #20 = Utf8               BootstrapMethods
  #21 = MethodHandle       6:#32          // REF_invokeStatic java/lang/invoke/StringConcatFactory.makeConcatWithConstants:(Ljava/lang/invoke/MethodHandles$Lookup;Ljava/lang/String;Ljava/lang/invoke/MethodType;Ljava/lang/String;[Ljava/lang/Object;)Ljava/lang/invoke/CallSite;
  #22 = String             #33            // Hello,\u0001
  #23 = NameAndType        #34:#35        // makeConcatWithConstants:(Ljava/lang/String;)Ljava/lang/String;
  #24 = Class              #36            // java/lang/System
  #25 = NameAndType        #37:#38        // out:Ljava/io/PrintStream;
  #26 = Class              #39            // java/io/PrintStream
  #27 = NameAndType        #40:#14        // println:(Ljava/lang/String;)V
  #28 = Utf8               Hello
  #29 = NameAndType        #13:#14        // foo:(Ljava/lang/String;)V
  #30 = Utf8               Test
  #31 = Utf8               java/lang/Object
  #32 = Methodref          #41.#42        // java/lang/invoke/StringConcatFactory.makeConcatWithConstants:(Ljava/lang/invoke/MethodHandles$Lookup;Ljava/lang/String;Ljava/lang/invoke/MethodType;Ljava/lang/String;[Ljava/lang/Object;)Ljava/lang/invoke/CallSite;
  #33 = Utf8               Hello,\u0001
  #34 = Utf8               makeConcatWithConstants
  #35 = Utf8               (Ljava/lang/String;)Ljava/lang/String;
  #36 = Utf8               java/lang/System
  #37 = Utf8               out
  #38 = Utf8               Ljava/io/PrintStream;
  #39 = Utf8               java/io/PrintStream
  #40 = Utf8               println
  #41 = Class              #43            // java/lang/invoke/StringConcatFactory
  #42 = NameAndType        #34:#47        // makeConcatWithConstants:(Ljava/lang/invoke/MethodHandles$Lookup;Ljava/lang/String;Ljava/lang/invoke/MethodType;Ljava/lang/String;[Ljava/lang/Object;)Ljava/lang/invoke/CallSite;
  #43 = Utf8               java/lang/invoke/StringConcatFactory
  #44 = Class              #49            // java/lang/invoke/MethodHandles$Lookup
  #45 = Utf8               Lookup
  #46 = Utf8               InnerClasses
  #47 = Utf8               (Ljava/lang/invoke/MethodHandles$Lookup;Ljava/lang/String;Ljava/lang/invoke/MethodType;Ljava/lang/String;[Ljava/lang/Object;)Ljava/lang/invoke/CallSite;
  #48 = Class              #50            // java/lang/invoke/MethodHandles
  #49 = Utf8               java/lang/invoke/MethodHandles$Lookup
  #50 = Utf8               java/lang/invoke/MethodHandles
{
  public Test();
    descriptor: ()V
    flags: (0x0001) ACC_PUBLIC
    Code:
      stack=1, locals=1, args_size=1
         0: aload_0
         1: invokespecial #1                  // Method java/lang/Object."<init>":()V
         4: return
      LineNumberTable:
        line 3: 0

  public static final void foo(java.lang.String);
    descriptor: (Ljava/lang/String;)V
    flags: (0x0019) ACC_PUBLIC, ACC_STATIC, ACC_FINAL
    Code:
      stack=2, locals=1, args_size=1
         0: aload_0
         1: invokedynamic #2,  0              // InvokeDynamic #0:makeConcatWithConstants:(Ljava/lang/String;)Ljava/lang/String;
         6: astore_0
         7: getstatic     #3                  // Field java/lang/System.out:Ljava/io/PrintStream;
        10: aload_0
        11: invokevirtual #4                  // Method java/io/PrintStream.println:(Ljava/lang/String;)V
        14: return
      LineNumberTable:
        line 5: 0
        line 6: 7
        line 7: 14

  public static final void main(java.lang.String[]);
    descriptor: ([Ljava/lang/String;)V
    flags: (0x0019) ACC_PUBLIC, ACC_STATIC, ACC_FINAL
    Code:
      stack=1, locals=1, args_size=1
         0: ldc           #5                  // String Hello
         2: invokestatic  #6                  // Method foo:(Ljava/lang/String;)V
         5: return
      LineNumberTable:
        line 9: 0
        line 10: 5
}
SourceFile: "Test.java"
InnerClasses:
  public static final #45= #44 of #48;    // Lookup=class java/lang/invoke/MethodHandles$Lookup of class java/lang/invoke/MethodHandles
BootstrapMethods:
  0: #21 REF_invokeStatic java/lang/invoke/StringConcatFactory.makeConcatWithConstants:(Ljava/lang/invoke/MethodHandles$Lookup;Ljava/lang/String;Ljava/lang/invoke/MethodType;Ljava/lang/String;[Ljava/lang/Object;)Ljava/lang/invoke/CallSite;
    Method arguments:
      #22 Hello,\u0001
